{
  "metainfo" : {
    "migrationVersions" : {
      "gemBuilderVersion" : "v1",
      "unitTestNullDataMigrated" : true
    },
    "functions" : {
      "businessRules" : {
        "rules" : [ ],
        "sharedRules" : [ ]
      }
    },
    "codeGenConfiguration" : {
      "editableConfig" : true,
      "plibVersion" : {
        "mavenVersion" : "8.6.0",
        "pyPiVersion" : "1.9.28"
      },
      "instrumentationEnabled" : true
    },
    "id" : "1",
    "uri" : "pipelines/demo_new",
    "sourceSuggestions" : [ ],
    "pipelineSettingsInfo" : {
      "applicationName" : "demo_new",
      "hasApplication" : true,
      "isFunctionsPackageDirDefined" : true,
      "isNullValuesInUnitTestsEnabled" : true
    },
    "language" : "python",
    "fabricId" : "9631",
    "frontEndLanguage" : "sql",
    "mode" : "batch",
    "udfs" : {
      "language" : "python",
      "udfs" : [ ],
      "functionPackageName" : "bobwprophecyioteam.helloworld.functions",
      "sharedFunctionPackageNames" : [ "prophecy.data_quality.functions", "prophecy.spark_basic.functions", "prophecy.streaming.functions", "prophecy.warehouse.functions", "maciejdemos.dataquality.functions" ]
    },
    "udafs" : {
      "language" : "python",
      "code" : ""
    },
    "configuration" : {
      "common" : {
        "type" : "record",
        "fields" : [ ]
      },
      "oldCommon" : {
        "type" : "record",
        "fields" : [ ]
      },
      "fabrics" : { },
      "instances" : { },
      "selected" : "default",
      "nonEditable" : [ ],
      "isSubscribedPipelineWithPipelineConfigs" : false
    },
    "sparkConf" : [ ],
    "hadoopConf" : [ ],
    "codeMode" : "sparse",
    "buildSystem" : "maven",
    "externalDependencies" : [ ],
    "dependentProjectExternalDependencies" : [ ],
    "isImported" : false,
    "interimMode" : "Full",
    "interimModeEnabled" : true,
    "visualCodeInterimMode" : "Full",
    "recordsLimit" : {
      "enabled" : true,
      "value" : 1000
    },
    "topLevelPackage" : "demo_new",
    "configurationVersion" : "v2"
  },
  "connections" : [ {
    "id" : "CxRj0Vsp",
    "source" : "mkZ3VRCE",
    "sourcePort" : "mPUd1ePo",
    "target" : "pECrxbH0",
    "targetPort" : "oHBfAe2L"
  }, {
    "id" : "ZgDGlSA5",
    "source" : "jcAURqpE",
    "sourcePort" : "yPygtHHi",
    "target" : "mkZ3VRCE",
    "targetPort" : "anjMIjBO"
  }, {
    "id" : "wA0V0NSI",
    "source" : "RMYbaBFI",
    "sourcePort" : "GHH7gt8q",
    "target" : "jcAURqpE",
    "targetPort" : "IVv9Zlxd"
  }, {
    "id" : "CCK71iIs",
    "source" : "IRbuJrnB-ffalXyy0bfDz$$s_SgdkB_DDfqyt4Apu1u3",
    "sourcePort" : "gT89dZGw0xGTrBE6e1Ng_$$Rchpy-38A_j2olMlSgBqe",
    "target" : "RMYbaBFI",
    "targetPort" : "U23K2aKB"
  }, {
    "id" : "P8TkJhL3",
    "source" : "TZIEqsEn",
    "sourcePort" : "M34WizN3",
    "target" : "ZfsRguwE",
    "targetPort" : "oECIIkme"
  }, {
    "id" : "boQJotDG",
    "source" : "CdZPwkHp",
    "sourcePort" : "zPkfO0Xy",
    "target" : "ZfsRguwE",
    "targetPort" : "zZTnoS25"
  }, {
    "id" : "Ka54S0DUPXaj-FlpVQrEH$$Wm1_FJnbkvNhMNRTt3bQW",
    "source" : "ZfsRguwE",
    "sourcePort" : "ZPO8w2Om",
    "target" : "IRbuJrnB-ffalXyy0bfDz$$s_SgdkB_DDfqyt4Apu1u3",
    "targetPort" : "NTl-xXkptcUjTYbuzEIxS$$xSm1UkaHuJmS08QdMhZeI"
  } ],
  "processes" : {
    "jcAURqpE" : {
      "id" : "jcAURqpE",
      "component" : "Reformat",
      "metadata" : {
        "label" : "total_sales_by_customer",
        "slug" : "total_sales_by_customer",
        "x" : 780,
        "y" : 120,
        "phase" : 0,
        "cache" : false,
        "detailedStats" : false,
        "isImported" : false
      },
      "ports" : {
        "inputs" : [ {
          "id" : "IVv9Zlxd",
          "slug" : "sales_summary_by_customer",
          "schema" : {
            "type" : "struct",
            "fields" : [ {
              "name" : "full_name",
              "type" : "string",
              "nullable" : true,
              "metadata" : {
                "description" : "",
                "mappings" : [ ],
                "tags" : [ ]
              }
            }, {
              "name" : "SUM_sales_amount",
              "type" : "double",
              "nullable" : true,
              "metadata" : {
                "description" : "",
                "mappings" : [ ],
                "tags" : [ ]
              }
            }, {
              "name" : "ORDER_COUNT",
              "type" : "long",
              "nullable" : false,
              "metadata" : {
                "description" : "",
                "mappings" : [ ],
                "tags" : [ ]
              }
            } ]
          },
          "isStreaming" : false
        } ],
        "outputs" : [ {
          "id" : "yPygtHHi",
          "slug" : "out"
        } ],
        "selectedInputFields" : [ ],
        "isCustomOutputSchema" : false,
        "autoUpdateOnRun" : false
      },
      "properties" : {
        "importLanguage" : "${$.workflow.metainfo.frontEndLanguage}",
        "expressions" : [ {
          "target" : "full_name",
          "expression" : {
            "format" : "sql",
            "expression" : "full_name"
          },
          "description" : ""
        }, {
          "target" : "TOTAL_SALES",
          "expression" : {
            "format" : "sql",
            "expression" : "ROUND(SUM_sales_amount, 2)"
          },
          "description" : ""
        }, {
          "target" : "ORDER_COUNT",
          "expression" : {
            "format" : "sql",
            "expression" : "ORDER_COUNT"
          },
          "description" : ""
        } ],
        "importString" : "",
        "activeTab" : "expressions",
        "columnsSelector" : [ ]
      },
      "componentInfo" : {
        "gemId" : "gitUri=http://gitserver:3000/DxEheDCJ_team_5751/DxEheDCJ_project_12654.git&subPath=&tag=0.2.39&projectSubscriptionProjectId=12654&path=gems/Reformat",
        "projectName" : "ProphecySparkBasicsPython"
      }
    },
    "TZIEqsEn" : {
      "id" : "TZIEqsEn",
      "component" : "Source",
      "metadata" : {
        "label" : "orders",
        "slug" : "orders",
        "x" : 20,
        "y" : 20,
        "phase" : 0,
        "cache" : false,
        "detailedStats" : false,
        "isImported" : false
      },
      "ports" : {
        "inputs" : [ ],
        "outputs" : [ {
          "id" : "M34WizN3",
          "slug" : "out"
        } ],
        "selectedInputFields" : [ ],
        "isCustomOutputSchema" : false,
        "autoUpdateOnRun" : false
      },
      "properties" : {
        "datasetId" : "datasets/orders"
      }
    },
    "RMYbaBFI" : {
      "id" : "RMYbaBFI",
      "component" : "Aggregate",
      "metadata" : {
        "label" : "sales_summary_by_customer",
        "slug" : "sales_summary_by_customer",
        "x" : 580,
        "y" : 120,
        "phase" : 0,
        "cache" : false,
        "detailedStats" : false,
        "isImported" : false
      },
      "ports" : {
        "inputs" : [ {
          "id" : "U23K2aKB",
          "slug" : "reformat_order_customer_details",
          "schema" : {
            "type" : "struct",
            "fields" : [ {
              "name" : "customer_id",
              "type" : "integer",
              "nullable" : true,
              "metadata" : {
                "description" : "Unique identifier for the customer who placed the order.",
                "mappings" : [ ],
                "tags" : [ ]
              }
            }, {
              "name" : "full_name",
              "type" : "string",
              "nullable" : true,
              "metadata" : {
                "description" : "",
                "mappings" : [ ],
                "tags" : [ ]
              }
            }, {
              "name" : "order_id",
              "type" : "integer",
              "nullable" : true,
              "metadata" : {
                "description" : "Unique identifier for each order placed by customers.",
                "mappings" : [ ],
                "tags" : [ ]
              }
            }, {
              "name" : "sales_amount",
              "type" : "double",
              "nullable" : true,
              "metadata" : {
                "description" : "Total monetary value of the order; Represents the cost associated with the order.",
                "mappings" : [ ],
                "tags" : [ ]
              }
            }, {
              "name" : "company_name",
              "type" : "string",
              "nullable" : true,
              "metadata" : {
                "description" : "",
                "mappings" : [ ],
                "tags" : [ ]
              }
            } ]
          },
          "isStreaming" : false
        } ],
        "outputs" : [ {
          "id" : "GHH7gt8q",
          "slug" : "out"
        } ],
        "selectedInputFields" : [ ],
        "isCustomOutputSchema" : false,
        "autoUpdateOnRun" : false
      },
      "properties" : {
        "allIns" : false,
        "doPivot" : false,
        "aggregate" : [ {
          "target" : "SUM_sales_amount",
          "expression" : {
            "format" : "sql",
            "expression" : "SUM(sales_amount)"
          },
          "description" : ""
        }, {
          "target" : "ORDER_COUNT",
          "expression" : {
            "format" : "sql",
            "expression" : "COUNT(order_id)"
          },
          "description" : ""
        } ],
        "allowSelection" : true,
        "pivotColumn" : null,
        "pivotValues" : [ ],
        "activeTab" : "aggregate",
        "columnsSelector" : [ ],
        "groupBy" : [ {
          "target" : "full_name",
          "expression" : {
            "format" : "sql",
            "expression" : "full_name"
          },
          "description" : ""
        } ]
      },
      "componentInfo" : {
        "gemId" : "gitUri=http://gitserver:3000/DxEheDCJ_team_5751/DxEheDCJ_project_12654.git&subPath=&tag=0.2.39&projectSubscriptionProjectId=12654&path=gems/Aggregate",
        "projectName" : "ProphecySparkBasicsPython"
      }
    },
    "CdZPwkHp" : {
      "id" : "CdZPwkHp",
      "component" : "Source",
      "metadata" : {
        "label" : "customers",
        "slug" : "customers",
        "x" : 20,
        "y" : 220,
        "phase" : 0,
        "cache" : false,
        "detailedStats" : false,
        "isImported" : false
      },
      "ports" : {
        "inputs" : [ ],
        "outputs" : [ {
          "id" : "zPkfO0Xy",
          "slug" : "out"
        } ],
        "selectedInputFields" : [ ],
        "isCustomOutputSchema" : false,
        "autoUpdateOnRun" : false
      },
      "properties" : {
        "datasetId" : "datasets/customers"
      }
    },
    "ZfsRguwE" : {
      "id" : "ZfsRguwE",
      "component" : "Join",
      "metadata" : {
        "label" : "order_customer_details",
        "slug" : "order_customer_details",
        "x" : 220,
        "y" : 120,
        "phase" : 0,
        "cache" : false,
        "detailedStats" : false,
        "isImported" : false
      },
      "ports" : {
        "inputs" : [ {
          "id" : "oECIIkme",
          "slug" : "orders",
          "schema" : {
            "type" : "struct",
            "fields" : [ {
              "name" : "order_id",
              "type" : "integer",
              "nullable" : true,
              "metadata" : {
                "description" : "Unique identifier for each order placed by customers.",
                "mappings" : [ ],
                "tags" : [ ]
              }
            }, {
              "name" : "customer_id",
              "type" : "integer",
              "nullable" : true,
              "metadata" : {
                "description" : "Unique identifier for the customer who placed the order.",
                "mappings" : [ ],
                "tags" : [ ]
              }
            }, {
              "name" : "order_status",
              "type" : "string",
              "nullable" : true,
              "metadata" : {
                "description" : "Current status of the order; Indicates whether the order is Finished, Started, or Approved.",
                "mappings" : [ ],
                "tags" : [ ]
              }
            }, {
              "name" : "order_category",
              "type" : "string",
              "nullable" : true,
              "metadata" : {
                "description" : "The category of the order, indicating the type of service or product being purchased.",
                "mappings" : [ ],
                "tags" : [ ]
              }
            }, {
              "name" : "order_date",
              "type" : "string",
              "nullable" : true,
              "metadata" : {
                "description" : "Date when the order was placed; Format is YYYY-MM-DD.",
                "mappings" : [ ],
                "tags" : [ ]
              }
            }, {
              "name" : "amount",
              "type" : "double",
              "nullable" : true,
              "metadata" : {
                "description" : "Total monetary value of the order; Represents the cost associated with the order.",
                "mappings" : [ ],
                "tags" : [ ]
              }
            } ]
          },
          "isStreaming" : false
        }, {
          "id" : "zZTnoS25",
          "slug" : "customers",
          "schema" : {
            "type" : "struct",
            "fields" : [ {
              "name" : "customer_id",
              "type" : "integer",
              "nullable" : true,
              "metadata" : {
                "description" : "Unique identifier for each customer in the dataset.",
                "mappings" : [ ],
                "tags" : [ ]
              }
            }, {
              "name" : "first_name",
              "type" : "string",
              "nullable" : true,
              "metadata" : {
                "description" : "The first name of the customer.",
                "mappings" : [ ],
                "tags" : [ ]
              }
            }, {
              "name" : "last_name",
              "type" : "string",
              "nullable" : true,
              "metadata" : {
                "description" : "The surname of the customer, used for identification and personalization.",
                "mappings" : [ ],
                "tags" : [ ]
              }
            }, {
              "name" : "phone",
              "type" : "string",
              "nullable" : true,
              "metadata" : {
                "description" : "Contact number of the customer; Format is a standard phone number.",
                "mappings" : [ ],
                "tags" : [ ]
              }
            }, {
              "name" : "email",
              "type" : "string",
              "nullable" : true,
              "metadata" : {
                "description" : "Email address of the customer; Used for communication and account-related notifications.",
                "mappings" : [ ],
                "tags" : [ ]
              }
            }, {
              "name" : "country_code",
              "type" : "string",
              "nullable" : true,
              "metadata" : {
                "description" : "ISO code representing the country of the customer.",
                "mappings" : [ ],
                "tags" : [ ]
              }
            }, {
              "name" : "account_open_date",
              "type" : "string",
              "nullable" : true,
              "metadata" : {
                "description" : "Date when the customer account was opened; Format is YYYY-MM-DD.",
                "mappings" : [ ],
                "tags" : [ ]
              }
            }, {
              "name" : "account_flags",
              "type" : "string",
              "nullable" : true,
              "metadata" : {
                "description" : "Flags indicating the status or special conditions of the customer's account; Typically used for categorizing accounts.",
                "mappings" : [ ],
                "tags" : [ ]
              }
            } ]
          },
          "isStreaming" : false
        } ],
        "outputs" : [ {
          "id" : "ZPO8w2Om",
          "slug" : "out"
        } ],
        "selectedInputFields" : [ ],
        "isCustomOutputSchema" : false,
        "autoUpdateOnRun" : false
      },
      "properties" : {
        "conditions" : [ {
          "alias" : "customers",
          "expression" : {
            "format" : "sql",
            "expression" : "orders.customer_id = customers.customer_id"
          },
          "joinType" : "inner"
        } ],
        "expressions" : [ {
          "target" : "order_id",
          "expression" : {
            "format" : "sql",
            "expression" : "orders.order_id"
          },
          "description" : ""
        }, {
          "target" : "customer_id",
          "expression" : {
            "format" : "sql",
            "expression" : "orders.customer_id"
          },
          "description" : ""
        }, {
          "target" : "order_status",
          "expression" : {
            "format" : "sql",
            "expression" : "orders.order_status"
          },
          "description" : ""
        }, {
          "target" : "order_category",
          "expression" : {
            "format" : "sql",
            "expression" : "orders.order_category"
          },
          "description" : ""
        }, {
          "target" : "order_date",
          "expression" : {
            "format" : "sql",
            "expression" : "orders.order_date"
          },
          "description" : ""
        }, {
          "target" : "amount",
          "expression" : {
            "format" : "sql",
            "expression" : "orders.amount"
          },
          "description" : ""
        }, {
          "target" : "first_name",
          "expression" : {
            "format" : "sql",
            "expression" : "customers.first_name"
          },
          "description" : ""
        }, {
          "target" : "last_name",
          "expression" : {
            "format" : "sql",
            "expression" : "customers.last_name"
          },
          "description" : ""
        }, {
          "target" : "phone",
          "expression" : {
            "format" : "sql",
            "expression" : "customers.phone"
          },
          "description" : ""
        }, {
          "target" : "email",
          "expression" : {
            "format" : "sql",
            "expression" : "customers.email"
          },
          "description" : ""
        }, {
          "target" : "country_code",
          "expression" : {
            "format" : "sql",
            "expression" : "customers.country_code"
          },
          "description" : ""
        }, {
          "target" : "account_open_date",
          "expression" : {
            "format" : "sql",
            "expression" : "customers.account_open_date"
          },
          "description" : ""
        }, {
          "target" : "account_flags",
          "expression" : {
            "format" : "sql",
            "expression" : "customers.account_flags"
          },
          "description" : ""
        } ],
        "hints" : [ {
          "id" : "orders",
          "alias" : "orders",
          "hintType" : "none",
          "propagateColumns" : false
        }, {
          "id" : "customers",
          "alias" : "customers",
          "hintType" : "none",
          "propagateColumns" : false
        } ],
        "allIn1" : null,
        "activeTab" : "conditions",
        "columnsSelector" : [ ],
        "allIn0" : null,
        "whereClause" : null,
        "headAlias" : "orders"
      },
      "componentInfo" : {
        "gemId" : "gitUri=http://gitserver:3000/DxEheDCJ_team_5751/DxEheDCJ_project_12654.git&subPath=&tag=0.2.39&projectSubscriptionProjectId=12654&path=gems/Join",
        "projectName" : "ProphecySparkBasicsPython"
      }
    },
    "mkZ3VRCE" : {
      "id" : "mkZ3VRCE",
      "component" : "OrderBy",
      "metadata" : {
        "label" : "total_sales_desc",
        "slug" : "total_sales_desc",
        "x" : 980,
        "y" : 120,
        "phase" : 0,
        "cache" : false,
        "detailedStats" : false,
        "isImported" : false
      },
      "ports" : {
        "inputs" : [ {
          "id" : "anjMIjBO",
          "slug" : "total_sales_by_customer",
          "schema" : {
            "type" : "struct",
            "fields" : [ {
              "name" : "full_name",
              "type" : "string",
              "nullable" : true,
              "metadata" : {
                "description" : "",
                "mappings" : [ ],
                "tags" : [ ]
              }
            }, {
              "name" : "TOTAL_SALES",
              "type" : "double",
              "nullable" : true,
              "metadata" : {
                "description" : "",
                "mappings" : [ ],
                "tags" : [ ]
              }
            }, {
              "name" : "ORDER_COUNT",
              "type" : "long",
              "nullable" : false,
              "metadata" : {
                "description" : "",
                "mappings" : [ ],
                "tags" : [ ]
              }
            } ]
          },
          "isStreaming" : false
        } ],
        "outputs" : [ {
          "id" : "mPUd1ePo",
          "slug" : "out"
        } ],
        "selectedInputFields" : [ ],
        "isCustomOutputSchema" : false,
        "autoUpdateOnRun" : false
      },
      "properties" : {
        "columnsSelector" : [ ],
        "orders" : [ {
          "expression" : {
            "format" : "sql",
            "expression" : "TOTAL_SALES"
          },
          "sortType" : "desc"
        } ]
      },
      "componentInfo" : {
        "gemId" : "gitUri=http://gitserver:3000/DxEheDCJ_team_5751/DxEheDCJ_project_12654.git&subPath=&tag=0.2.39&projectSubscriptionProjectId=12654&path=gems/OrderBy",
        "projectName" : "ProphecySparkBasicsPython"
      }
    },
    "pECrxbH0" : {
      "id" : "pECrxbH0",
      "component" : "Limit",
      "metadata" : {
        "label" : "limited_sort_results",
        "slug" : "limited_sort_results",
        "x" : 1180,
        "y" : 120,
        "phase" : 0,
        "cache" : false,
        "detailedStats" : false,
        "isImported" : false
      },
      "ports" : {
        "inputs" : [ {
          "id" : "oHBfAe2L",
          "slug" : "total_sales_desc",
          "schema" : {
            "type" : "struct",
            "fields" : [ {
              "name" : "full_name",
              "type" : "string",
              "nullable" : true,
              "metadata" : {
                "description" : "",
                "mappings" : [ ],
                "tags" : [ ]
              }
            }, {
              "name" : "TOTAL_SALES",
              "type" : "double",
              "nullable" : true,
              "metadata" : {
                "description" : "",
                "mappings" : [ ],
                "tags" : [ ]
              }
            }, {
              "name" : "ORDER_COUNT",
              "type" : "long",
              "nullable" : false,
              "metadata" : {
                "description" : "",
                "mappings" : [ ],
                "tags" : [ ]
              }
            } ]
          },
          "isStreaming" : false
        } ],
        "outputs" : [ {
          "id" : "vGXGYzIR",
          "slug" : "out"
        } ],
        "selectedInputFields" : [ ],
        "isCustomOutputSchema" : false,
        "autoUpdateOnRun" : false
      },
      "properties" : {
        "limit" : "25"
      },
      "componentInfo" : {
        "gemId" : "gitUri=http://gitserver:3000/DxEheDCJ_team_5751/DxEheDCJ_project_12654.git&subPath=&tag=0.2.39&projectSubscriptionProjectId=12654&path=gems/Limit",
        "projectName" : "ProphecySparkBasicsPython"
      }
    },
    "IRbuJrnB-ffalXyy0bfDz$$s_SgdkB_DDfqyt4Apu1u3" : {
      "id" : "IRbuJrnB-ffalXyy0bfDz$$s_SgdkB_DDfqyt4Apu1u3",
      "component" : "Reformat",
      "metadata" : {
        "label" : "reformat_order_customer_details",
        "slug" : "reformat_order_customer_details",
        "x" : 380,
        "y" : 120,
        "phase" : 0,
        "cache" : false,
        "detailedStats" : false,
        "isImported" : false,
        "comment" : "Enhances order customer details by creating a full name field and extracting the company name from email addresses.",
        "autoUpdateComment" : true
      },
      "ports" : {
        "inputs" : [ {
          "id" : "NTl-xXkptcUjTYbuzEIxS$$xSm1UkaHuJmS08QdMhZeI",
          "slug" : "order_customer_details",
          "schema" : {
            "type" : "struct",
            "fields" : [ {
              "name" : "order_id",
              "type" : "integer",
              "nullable" : true,
              "metadata" : {
                "description" : "Unique identifier for each order placed by customers.",
                "mappings" : [ ],
                "tags" : [ ]
              }
            }, {
              "name" : "customer_id",
              "type" : "integer",
              "nullable" : true,
              "metadata" : {
                "description" : "Unique identifier for the customer who placed the order.",
                "mappings" : [ ],
                "tags" : [ ]
              }
            }, {
              "name" : "order_status",
              "type" : "string",
              "nullable" : true,
              "metadata" : {
                "description" : "Current status of the order; Indicates whether the order is Finished, Started, or Approved.",
                "mappings" : [ ],
                "tags" : [ ]
              }
            }, {
              "name" : "order_category",
              "type" : "string",
              "nullable" : true,
              "metadata" : {
                "description" : "The category of the order, indicating the type of service or product being purchased.",
                "mappings" : [ ],
                "tags" : [ ]
              }
            }, {
              "name" : "order_date",
              "type" : "string",
              "nullable" : true,
              "metadata" : {
                "description" : "Date when the order was placed; Format is YYYY-MM-DD.",
                "mappings" : [ ],
                "tags" : [ ]
              }
            }, {
              "name" : "amount",
              "type" : "double",
              "nullable" : true,
              "metadata" : {
                "description" : "Total monetary value of the order; Represents the cost associated with the order.",
                "mappings" : [ ],
                "tags" : [ ]
              }
            }, {
              "name" : "first_name",
              "type" : "string",
              "nullable" : true,
              "metadata" : {
                "description" : "The first name of the customer.",
                "mappings" : [ ],
                "tags" : [ ]
              }
            }, {
              "name" : "last_name",
              "type" : "string",
              "nullable" : true,
              "metadata" : {
                "description" : "The surname of the customer, used for identification and personalization.",
                "mappings" : [ ],
                "tags" : [ ]
              }
            }, {
              "name" : "phone",
              "type" : "string",
              "nullable" : true,
              "metadata" : {
                "description" : "Contact number of the customer; Format is a standard phone number.",
                "mappings" : [ ],
                "tags" : [ ]
              }
            }, {
              "name" : "email",
              "type" : "string",
              "nullable" : true,
              "metadata" : {
                "description" : "Email address of the customer; Used for communication and account-related notifications.",
                "mappings" : [ ],
                "tags" : [ ]
              }
            }, {
              "name" : "country_code",
              "type" : "string",
              "nullable" : true,
              "metadata" : {
                "description" : "ISO code representing the country of the customer.",
                "mappings" : [ ],
                "tags" : [ ]
              }
            }, {
              "name" : "account_open_date",
              "type" : "string",
              "nullable" : true,
              "metadata" : {
                "description" : "Date when the customer account was opened; Format is YYYY-MM-DD.",
                "mappings" : [ ],
                "tags" : [ ]
              }
            }, {
              "name" : "account_flags",
              "type" : "string",
              "nullable" : true,
              "metadata" : {
                "description" : "Flags indicating the status or special conditions of the customer's account; Typically used for categorizing accounts.",
                "mappings" : [ ],
                "tags" : [ ]
              }
            } ]
          },
          "isStreaming" : false
        } ],
        "outputs" : [ {
          "id" : "gT89dZGw0xGTrBE6e1Ng_$$Rchpy-38A_j2olMlSgBqe",
          "slug" : "out"
        } ],
        "selectedInputFields" : [ ],
        "isCustomOutputSchema" : false,
        "autoUpdateOnRun" : false
      },
      "properties" : {
        "importLanguage" : "${$.workflow.metainfo.frontEndLanguage}",
        "expressions" : [ {
          "target" : "customer_id",
          "expression" : {
            "format" : "sql",
            "expression" : "customer_id"
          },
          "description" : ""
        }, {
          "target" : "full_name",
          "expression" : {
            "format" : "sql",
            "expression" : "concat(first_name, ' ', last_name)"
          },
          "description" : ""
        }, {
          "target" : "order_id",
          "expression" : {
            "format" : "sql",
            "expression" : "order_id"
          },
          "description" : ""
        }, {
          "target" : "sales_amount",
          "expression" : {
            "format" : "sql",
            "expression" : "amount"
          },
          "description" : ""
        }, {
          "target" : "company_name",
          "expression" : {
            "format" : "sql",
            "expression" : "substring_index(email, '@', -1)"
          },
          "description" : ""
        } ],
        "importString" : "",
        "activeTab" : "expressions",
        "columnsSelector" : [ "NTl-xXkptcUjTYbuzEIxS$$xSm1UkaHuJmS08QdMhZeI##last_name", "NTl-xXkptcUjTYbuzEIxS$$xSm1UkaHuJmS08QdMhZeI##order_id", "NTl-xXkptcUjTYbuzEIxS$$xSm1UkaHuJmS08QdMhZeI##first_name", "NTl-xXkptcUjTYbuzEIxS$$xSm1UkaHuJmS08QdMhZeI##amount", "NTl-xXkptcUjTYbuzEIxS$$xSm1UkaHuJmS08QdMhZeI##email", "NTl-xXkptcUjTYbuzEIxS$$xSm1UkaHuJmS08QdMhZeI##customer_id" ]
      },
      "componentInfo" : {
        "gemId" : "gitUri=http://gitserver:3000/DxEheDCJ_team_5751/DxEheDCJ_project_12654.git&subPath=&tag=0.2.39&projectSubscriptionProjectId=12654&path=gems/Reformat",
        "projectName" : "ProphecySparkBasicsPython"
      }
    }
  },
  "ports" : {
    "inputs" : [ ],
    "outputs" : [ ],
    "selectedInputFields" : [ ],
    "isCustomOutputSchema" : false,
    "autoUpdateOnRun" : false
  }
}